[
    {
        "number": 1,
        "name": "Your Apply",
        "descr": "English Learning looking for random paragraphs, you've come to the right place."
    },
    {
        "number": 2,
        "name": "We Connect",
        "descr": "Javascript Learning looking for random paragraphs, you've come to the right place."
    },
    {
        "number": 3,
        "name": "You Get Ready",
        "descr": "Angular Learning looking for random paragraphs, you've come to the right place."
    },
    {
        "number": 4,
        "name": "Completed",
        "descr": "Php Learning looking for random paragraphs, you've come to the right place."
    }
]